openvpn_reconnect/__init__.py
openvpn_reconnect/__main__.py
openvpn_reconnect/daemon/__init__.py
openvpn_reconnect/daemon/daemon.py
openvpn_reconnect/daemon/daemon_reconnect.py
openvpn_reconnect/program/__init__.py
openvpn_reconnect/program/parser.py
openvpn_reconnect/program/reconnect.py
openvpn_reconnect/program/statics.py
openvpn_reconnect-1.0.0.post3.dist-info/DESCRIPTION.rst
openvpn_reconnect-1.0.0.post3.dist-info/METADATA
openvpn_reconnect-1.0.0.post3.dist-info/RECORD
openvpn_reconnect-1.0.0.post3.dist-info/WHEEL
openvpn_reconnect-1.0.0.post3.dist-info/entry_points.txt
openvpn_reconnect-1.0.0.post3.dist-info/metadata.json
openvpn_reconnect-1.0.0.post3.dist-info/top_level.txt
openvpn_reconnect-1.0.0.post3.dist-info/zip-safe
